MANIFEST.in
README.rst
setup.py
justcoin/__init__.py
justcoin/justcoin.py
justcoin_sdk.egg-info/PKG-INFO
justcoin_sdk.egg-info/SOURCES.txt
justcoin_sdk.egg-info/dependency_links.txt
justcoin_sdk.egg-info/requires.txt
justcoin_sdk.egg-info/top_level.txt