Metadata-Version: 1.1
Name: justcoin-sdk
Version: 0.0.9
Summary: Python SDK for the Justcoin API
Home-page: https://github.com/vascop/justcoin-sdk
Author: Vasco Pinho
Author-email: vascogpinho@gmail.com
License: MIT
Download-URL: https://github.com/vascop/justcoin-sdk/zipball/master
Keywords: sdk,justcoin,api
Platform: UNKNOWN
Classifier: Programming Language :: Python
Classifier: Development Status :: 3 - Alpha
Classifier: Intended Audience :: Developers
Classifier: License :: OSI Approved :: MIT License
Classifier: Topic :: Internet
